{
  "shot_Normal_Accuracy_ShotAccuracy_Weight": 0.007618,
  "shot_Normal_Accuracy_RandomMin": -0.04815,
  "shot_Normal_Accuracy_RandomMax": 0.053008,
  "shot_Normal_Accuracy_Default": 0.208029,
  "shot_Normal_Accuracy_CornerShot_Weight": 0.009424,
  "shot_Normal_Accuracy_Weight_Angle": 1,
  "shot_Normal_Accuracy_FirstTouch_Weight": 0.009544,
  "shot_Normal_Accuracy_Volley_Weight": 0.009149,
  "shot_Normal_Power_ShotPower_Weight": 0.005643,
  "shot_Normal_Power_Gauge_Weight": 0.316796,
  "shot_Normal_Power_Default": 0.152541,
  "shot_Normal_Power_RunUp_Weight": 0.018622,
  "shot_Normal_Power_RunDistance_Weight": 0.009329,
  "shot_Normal_Power_OffesiveAwareness_Ratio": 0.198642,
  "shot_Normal_Power_Balance_Weight": 0.009813,
  "shot_Normal_Power_Composure_Weight": 0.013093,
  "shot_Normal_Power_LongShot_Weight": 0.010929,
  "shot_Normal_Power_FirstTouch_Weight": 0.009415,
  "shot_Normal_Power_Volley_Weight": 0.009617,
  "shot_Normal_Height_Gauge_SOT": 0.762401,
  "shot_Normal_Height_SOT": 2.633351,
  "shot_Normal_Height_MaxAngle": 28,
  "shot_Normal_Height_MaxHeight": 4.667449,
  "shot_Normal_Height_GroundGauge": 0.266319,
  "shot_HitEvent_endline_Range_Min": 4,
  "shot_HitEvent_endline_Range_Max": 6,
  "shot_HitEvent_endline_Height_Min": 3,
  "shot_HitEvent_endline_Height_Max": 5,
  "shot_HitEvent_sideline_Range_Min": 5,
  "shot_HitEvent_sideline_Range_Max": 14,
  "shot_HitEvent_sideline_Height_Min": 3,
  "shot_HitEvent_sideline_Height_Max": 5,
  "shot_HitEvent_halfline_Range_Min": 5,
  "shot_HitEvent_halfline_Range_Max": 14,
  "shot_HitEvent_halfline_Height_Min": 3,
  "shot_HitEvent_halfline_Height_Max": 5,
  "shot_Header_Accuracy_CornerShot_Weight": 0.002943,
  "shot_Header_Accuracy_LongShot_Weight": 0,
  "shot_Volley_Accuracy_CornerShot_Weight": 0.002971,
  "shot_Volley_Accuracy_LongShot_Weight": 0.003149,
  "shot_HAndV_Accuracy_OffesiveAwareness_Ratio": 0.189994,
  "shot_HAndV_Accuracy_Balance_Weight": 0.004962,
  "shot_HAndV_Accuracy_Composure_Weight": 0.005304,
  "shot_HandV_Accuracy_OneTouch_Weight": 0.649571,
  "shot_HAndV_Power_RunUp_Weight": 0.009024,
  "shot_HAndV_Power_RunDistance_Weight": 1,
  "shot_HAndV_Power_OffesiveAwareness_Ratio": 0.219303,
  "shot_HAndV_Power_Balance_Weight": 0.009261,
  "shot_HAndV_Power_OneTouch_Weight": 1,
  "shot_HAndV_Power_Composure_Weight": 0.009744,
  "shot_Header_Accuracy_Header_Ratio": 0.820848,
  "shot_Header_Accuracy_Header_Weight": 0.010289,
  "shot_Header_Accuracy_RandomMin": -0.304939,
  "shot_Header_Accuracy_RandomMax": 0.095176,
  "shot_Volley_Accuracy_RandomMin": -0.106255,
  "shot_Volley_Accuracy_RandomMax": 0.090436,
  "shot_Volley_Accuracy_Volley_Weight": 0.009129,
  "shot_Volley_Accuracy_Volley_Ratio": 0.864399,
  "shot_Volley_Accuracy_Default": 0.098869,
  "shot_Header_Power_Header_Weight": 0.007406,
  "shot_Header_Power_RandomMin": 0.108102,
  "shot_Header_Power_RandomMax": 0.319761,
  "shot_Volley_Power_Volley_Ratio": 0.773048,
  "shot_Volley_Power_Volley_Weight": 0.007268,
  "shot_Volley_Power_Volley_Default": 0.19844,
  "shot_Header_BallSpd_Weight": 14,
  "shot_Kick_Height_MinAngle": -20,
  "shot_Kick_Height_MaxAngle": 21,
  "shot_Header_Height_MinAngle": -44,
  "shot_Header_Height_MaxAngle": 27,
  "time_RunforKick_Shoot": 0.310993,
  "shoot_Normal_Height_Max": 266,
  "shoot_AddPoint_Min": 0.094294,
  "shoot_AddPoint_Max": 0.187486,
  "shoot_Header_AddPoint_Min": 0,
  "shoot_Header_AddPoint_Max": 0.286791,
  "shoot_Header_Addpower_Min": 0.107668,
  "shoot_Header_Addpower_Max": 0.272079,
  "shoot_Valid_HorizontalAngle": 31,
  "shoot_CrossbarHitChance": 9,
  "shoot_CrossbarHit_Fail_Min": 0.431559,
  "shoot_CrossbarHit_Fail_Max": 0.491199,
  "shoot_CrossbarHit_Success_Min": 0.909124,
  "shoot_Point_AreaLeft": 0.456098,
  "shoot_Point_AreaRight": 0.477978,
  "shoot_Point_AreaCenter": 1,
  "shoot_Point_Gauge10": 1,
  "shoot_Point_Gauge20": 0.969237,
  "shoot_Point_Gauge30": 0.80413,
  "shoot_Point_Gauge40": 0.718306,
  "shoot_Point_Gauge50": 0.63626,
  "shoot_Point_Gauge60": 0.529485,
  "shoot_Point_Gauge70": 1,
  "shoot_Point_Gauge80": 0.845107,
  "shoot_Point_Gauge90": 0.485911,
  "shoot_Point_Gauge100": 0.201781,
  "shoot_Point_Pressure0": 1,
  "shoot_Point_Pressure1": 0.757775,
  "shoot_Point_Pressure2": 0.300144,
  "shoot_Point_PressureCharging": 0.097768,
  "shoot_Point_Angle17": 0,
  "shoot_Point_Angle20": 0.374385,
  "shoot_Point_Angle25": 0.674643,
  "shoot_Point_Angle30": 0.755043,
  "shoot_Point_Angle40": 0.971238,
  "shoot_Point_Angle40Over": 1,
  "shoot_Point_Corss": 1,
  "shoot_Point_Lobbing": 0.658984,
  "shoot_Point_LooseBall": 0.402355,
  "shoot_Point_DirectionLow0": 1,
  "shoot_Point_DirectionLow45": 1,
  "shoot_Point_DirectionLow90": 0.766357,
  "shoot_Point_DirectionLow135": 0,
  "shoot_Point_DirectionLow180": 0,
  "shoot_Point_DirectionKnee0": 1,
  "shoot_Point_DirectionKnee45": 0.825098,
  "shoot_Point_DirectionKnee90": 0.476653,
  "shoot_Point_DirectionKnee135": 0,
  "shoot_Point_DirectionKnee180": 0,
  "shoot_Point_DirectionChest0": 1,
  "shoot_Point_DirectionChest45": 0.758416,
  "shoot_Point_DirectionChest90": 0.455591,
  "shoot_Point_DirectionChest135": 0,
  "shoot_Point_DirectionChest180": 0,
  "shoot_Point_DirectionHead0": 0.879423,
  "shoot_Point_DirectionHead45": 0.566329,
  "shoot_Point_DirectionHead90": 0.42772,
  "shoot_Point_DirectionHead135": 0,
  "shoot_Point_DirectionHead180": 0,
  "shoot_Clear_LineOutChance": 32,
  "shoot_Clear_Range_Min": 2913,
  "shoot_Clear_Range_Max": 3204,
  "shoot_Clear_Header_Range_Min": 1069,
  "shoot_Clear_Header_Range_Max": 935,
  "shoot_Clear_OutOfGround_Scale": 1.357666,
  "shoot_Direction_Center": 6,
  "shooting_Accuracy_Angle_Min": 21,
  "shooting_Accuracy_Angle_Max": 43,
  "shooting_Accuracy_Angle_Default": -0.724513,
  "shooting_Accuracy_Distance_Min": 5,
  "shooting_Accuracy_Distance_Max": 22,
  "shooting_Accuracy_Distance_Weight": -1,
  "shooting_Accuracy_LongShot_Weight": 0.010126,
  "shoot_Power_Weight": 0.075012,
  "shoot_Power_Default": 22,
  "shoot_Power_Distance_Max": 3229,
  "shoot_Power_Distance_Min": 0,
  "shoot_Power_Distance_Weight": 25,
  "shoot_Power_Gauge_Max": 77,
  "shoot_Power_Gauge_Min": 20,
  "shootPower_DribbleKick_Ratio": 0.734441,
  "shootPower_DirectKick_Ratio": 0.189305,
  "shootPower_RepulsiveRatio_Min": -0.047188,
  "shootPower_Repulsive_Default": 25,
  "headerShoot_Power_Default": 9,
  "headerShoot_Power_Weight": 5,
  "shootPower_Header_DirectKick_Ratio": 0.094029,
  "shootPower_Header_Distance_Max": 1389,
  "shootPower_Header_Distance_Min": 0,
  "shootPower_Header_Distance_Weight": 5,
  "header_Shot_Vertical_Point_Ratio": 0.325127,
  "header_Shot_Min_Header_Stat": 64,
  "header_Shot_Max_Header_Stat": 87,
  "header_Shot_Power_Random_Score_Min": -0.135657,
  "header_Shot_Power_Random_Score_Max": 0.152598,
  "header_Max_Goal_Post_Height": 3.792057,
  "header_Shot_Vertical_Norm_Score": 0.421949,
  "header_All_Accuracy_PressureScore": -0.320789,
  "header_All_Accuracy_Height_Ratio": 0.536067,
  "header_All_Accuracy_Header_Weight": 0.008737,
  "header_QueenBomber_Accuracy_PressureScore": -0.877246,
  "shot_Accuracy_Weight": 0.010884,
  "shot_Accuracy_Default": 0.293736,
  "shot_Accuracy_Gauge_Min": 0.184041,
  "shot_Power_Weight": 0.009604,
  "shot_FirstTouch_Weight": 0.005564,
  "shot_LongShot_Weight": 0.009315,
  "shot_Accuracy_Angle_Min": 16,
  "shot_Accuracy_Angle_Max": 42,
  "shot_Accuracy_Angle_Default": -0.436853,
  "shot_Accuracy_Distance_Min": 5,
  "shot_Accuracy_Distance_Max": 14,
  "shot_Accuracy_Distance_Weight": -1,
  "shot_Accuracy_Pressure_Max_Distance": 5,
  "shot_Accuracy_Pressure_Number_Weight": 0.922904,
  "shot_Accuracy_Pressure_Radius_Scale": 3,
  "shot_Accuracy_Pressure_Point_Angle": 28,
  "shot_Accuracy_Pressure_Angle_In": 0.508895,
  "shot_Accuracy_Pressure_Distance_Ratio": 0.187014,
  "shot_Normal_Accuracy_OffesiveAwareness_Ratio": 0.192273,
  "shot_Normal_Accuracy_Balance_Weight": 0.010377,
  "shot_Normal_Accuracy_Composure_Weight": 0.006941,
  "shot_Spread_Default": 0.104577,
  "shot_Spread_Normal_Weight": -1,
  "shot_Spread_OneTouch_Weight": -0.435896,
  "shot_Spread_Distance_Weight": 0.097832,
  "shot_Spread_Gap": 0.109886,
  "forced_Goal_Rotation_Cut": 98,
  "forced_Goal_GK_Disadvantage_Distance": 6.798574,
  "forced_Goal_GK_Disadvantage_Ratio": 0.816382,
  "forced_Goal_GK_Relative_Distance": 0.758945,
  "forced_Goal_Zone_Radius": 8.201298,
  "forced_Goal_Zone_Angle": 127,
  "shot_Hustle_OffensiveAwareness_Ratio": 0.202622,
  "shot_Hustle_Bravery_Weight": 0.010873,
  "shot_Hustle_Kick_Distance_Max": 2.320322,
  "shot_Hustle_Kick_Distance_Min": 0,
  "shot_Hustle_Best_Range_Penalty_Max": -0.104907,
  "shot_Hustle_Worst_Range_Penalty_Max": -0.28428,
  "shot_Hustle_Best_Range_Penalty_Min": 0,
  "shot_Hustle_Worst_Range_Penalty_Min": -0.164471,
  "kick_Weak_AnimRate_Fastest": 1.493724,
  "kick_Weak_AnimRate_Slowest": 1.50789,
  "kick_Weak_RootMotionScale": 0.764482,
  "kick_Power_AnimRate_Fastest": 1.666869,
  "kick_Power_AnimRate_Slowest": 1.233385,
  "kick_Power_RootMotionScale": 0.897416,
  "kick_Clear_AnimRate": 1.187191,
  "kick_Clear_RootMotionScale": 0.793884,
  "kickFeint_AnimRate_Default": 1.13989,
  "kickFeint_RootMotionScale_Default": 0.760995,
  "kickFeint_TouchInterval_Max": 0.190266,
  "curvedShoot_Torque_Scale": {
    "x": 25.34419,
    "y": 24.757046
  },
  "curvedShoot_Torque_Angle": 80.617962,
  "curvedShoot_Speed_Scale": 1.203494,
  "curvedShoot_Speed_Min": 41.018264,
  "curvedShoot_Speed_Max": 43,
  "curvedShoot_Weak_Torque_Scale": {
    "x": 17.475787,
    "y": 21.954207
  },
  "curvedShoot_Weak_Torque_Angle": 88.305419,
  "curvedShoot_Weak_Speed_Scale": 1.058329,
  "curvedShoot_Weak_Speed_Min": 27.387191,
  "curvedShoot_Weak_Speed_Max": 34.86633,
  "cannonShoot_Speed_Scale": 1.184723,
  "cannonShoot_Speed_Min": 31,
  "cannonShoot_Speed_Max": 44.295237,
  "bBBK_Inertia_Weight": 0.731794,
  "bBBK_Basic_Inertia_Probability": 0.534576,
  "bBBK_Inertia_Balance_Weight": 0.001918,
  "bBBK_Balance_Normalization": 58,
  "bBBK_Balance_Weight": 2
}